{
  "by_key": {
    "L001": [
      "ru",
      "10",
      3667,
      0
    ],
    "L002": [
      "ru",
      "12",
      987,
      0
    ],
    "L003": [
      "ru",
      "14",
      2071,
      0
    ],
    "L004": [
      "ru",
      "14",
      2126,
      0
    ],
    "L005": [
      "ru",
      "16",
      787,
      0
    ],
    "L006": [
      "ru",
      "20",
      688,
      0
    ],
    "L007": [
      "ru",
      "23",
      542,
      0
    ],
    "L008": [
      "ru",
      "25",
      5888,
      0
    ],
    "L009": [
      "ru",
      "25",
      5961,
      0
    ],
    "L010": [
      "ru",
      "31",
      7807,
      0
    ],
    "L011": [
      "ru",
      "33",
      4481,
      0
    ],
    "L012": [
      "ru",
      "36",
      7711,
      0
    ],
    "L013": [
      "ru",
      "52",
      1581,
      0
    ],
    "L014": [
      "ru",
      "52",
      17461,
      0
    ],
    "L015": [
      "ru",
      "54",
      322,
      0
    ],
    "L016": [
      "ru",
      "59",
      179,
      0
    ],
    "L017": [
      "ru",
      "60",
      4326,
      0
    ],
    "L018": [
      "ru",
      "60",
      4522,
      0
    ],
    "L019": [
      "ru",
      "63",
      10660,
      0
    ],
    "L020": [
      "ru",
      "63",
      10727,
      0
    ],
    "L021": [
      "ru",
      "64",
      36673,
      0
    ],
    "L022": [
      "ru",
      "66",
      4584,
      0
    ],
    "L023": [
      "ru",
      "66",
      4643,
      0
    ],
    "L024": [
      "ru",
      "66",
      6391,
      0
    ],
    "L025": [
      "ru",
      "66",
      7306,
      0
    ],
    "L026": [
      "ru",
      "71",
      2074,
      0
    ],
    "L027": [
      "ru",
      "71",
      4159,
      0
    ],
    "L028": [
      "ru",
      "71",
      4168,
      0
    ],
    "L029": [
      "ru",
      "71",
      4326,
      0
    ],
    "L030": [
      "ru",
      "71",
      5154,
      0
    ]
  },
  "text_hash_by_key": {
    "L001": "dfc446abf6c676be",
    "L002": "e39188957895ef81",
    "L003": "a19387819a03ee40",
    "L004": "aa75526a0350899a",
    "L005": "1696e13c9a6842d8",
    "L006": "c900ea88383972f4",
    "L007": "8b3c1d3f07221e98",
    "L008": "e657e0a4a66cbd89",
    "L009": "3c83685b520a9482",
    "L010": "a3d3073672bba4df",
    "L011": "34d8fd19ae5edb9b",
    "L012": "e505d2a5912fea9c",
    "L013": "5a3b0644d3803e84",
    "L014": "96c33591ed906019",
    "L015": "6701eacf2b700b26",
    "L016": "4e22b0c8befb99a6",
    "L017": "909a6731ad0878dc",
    "L018": "ee9697a14619121c",
    "L019": "2965fe202446ce7d",
    "L020": "403a76c21bcb58bf",
    "L021": "1afd3931a7be5d3a",
    "L022": "06bfa6e648ed6023",
    "L023": "7b159b8a1ef7ec70",
    "L024": "a1a53eefb73328a6",
    "L025": "cdf047e7c44671bc",
    "L026": "02146b292989a51f",
    "L027": "d57b8ad71e3c3978",
    "L028": "9a612ae9042c7553",
    "L029": "4a37abd952673f56",
    "L030": "a5d79b5abebadf40"
  },
  "item_by_key": {
    "L001": "b10-r0",
    "L002": "b12-r0",
    "L003": "b14-r0",
    "L004": "b14-r0",
    "L005": "b16-r0",
    "L006": "b20-r0",
    "L007": "b23-r0",
    "L008": "b25-r0",
    "L009": "b25-r0",
    "L010": "b31-r0",
    "L011": "b33-r0",
    "L012": "b36-r0",
    "L013": "b52-r0",
    "L014": "b52-r1",
    "L015": "b54-r0",
    "L016": "b59-r0",
    "L017": "b60-r0s0",
    "L018": "b60-r0s1",
    "L019": "b63-r0",
    "L020": "b63-r0",
    "L021": "b64-r0",
    "L022": "b66-r0s0",
    "L023": "b66-r0s0",
    "L024": "b66-r0s1",
    "L025": "b66-r0s2",
    "L026": "b71-r0",
    "L027": "b71-r1s0",
    "L028": "b71-r1s0",
    "L029": "b71-r1s1",
    "L030": "b71-r2"
  }
}