{
  "by_key": {
    "L001": [
      "en",
      "01",
      53,
      0
    ],
    "L002": [
      "en",
      "01",
      293,
      0
    ],
    "L003": [
      "en",
      "01",
      984,
      0
    ],
    "L004": [
      "en",
      "01",
      1434,
      0
    ],
    "L005": [
      "en",
      "01",
      2305,
      0
    ],
    "L006": [
      "en",
      "01",
      2652,
      0
    ],
    "L007": [
      "en",
      "01",
      2964,
      0
    ],
    "L008": [
      "en",
      "01",
      3142,
      0
    ],
    "L009": [
      "en",
      "01",
      4110,
      0
    ],
    "L010": [
      "en",
      "01",
      4553,
      0
    ],
    "L011": [
      "en",
      "01",
      4645,
      0
    ],
    "L012": [
      "en",
      "01",
      4909,
      0
    ],
    "L013": [
      "en",
      "01",
      5236,
      0
    ],
    "L014": [
      "en",
      "01",
      6651,
      0
    ],
    "L015": [
      "en",
      "01",
      7083,
      0
    ],
    "L016": [
      "en",
      "01",
      7237,
      0
    ],
    "L017": [
      "en",
      "01",
      7500,
      0
    ],
    "L018": [
      "en",
      "01",
      7764,
      0
    ],
    "L019": [
      "en",
      "01",
      7886,
      0
    ],
    "L020": [
      "en",
      "02",
      163,
      0
    ],
    "L021": [
      "en",
      "02",
      204,
      2
    ],
    "L022": [
      "en",
      "02",
      485,
      2
    ],
    "L023": [
      "en",
      "02",
      1071,
      4
    ],
    "L024": [
      "en",
      "02",
      1099,
      0
    ],
    "L025": [
      "en",
      "02",
      1145,
      8
    ],
    "L026": [
      "en",
      "02",
      1351,
      0
    ],
    "L027": [
      "en",
      "03",
      151,
      0
    ],
    "L028": [
      "en",
      "03",
      325,
      0
    ],
    "L029": [
      "en",
      "03",
      499,
      3
    ],
    "L030": [
      "en",
      "03",
      856,
      0
    ],
    "L031": [
      "en",
      "03",
      951,
      1
    ],
    "L032": [
      "en",
      "03",
      1029,
      0
    ],
    "L033": [
      "en",
      "03",
      1088,
      0
    ],
    "L034": [
      "en",
      "03",
      1175,
      2
    ],
    "L035": [
      "en",
      "03",
      1373,
      0
    ],
    "L036": [
      "en",
      "04",
      62,
      0
    ],
    "L037": [
      "en",
      "04",
      124,
      3
    ],
    "L038": [
      "en",
      "04",
      507,
      0
    ],
    "L039": [
      "en",
      "05",
      26,
      0
    ],
    "L040": [
      "en",
      "05",
      50,
      3
    ],
    "L041": [
      "en",
      "05",
      63,
      0
    ],
    "L042": [
      "en",
      "06",
      39,
      0
    ],
    "L043": [
      "en",
      "06",
      246,
      3
    ],
    "L044": [
      "en",
      "06",
      484,
      1
    ],
    "L045": [
      "en",
      "06",
      1132,
      0
    ],
    "L046": [
      "en",
      "06",
      1362,
      4
    ],
    "L047": [
      "en",
      "06",
      1516,
      0
    ],
    "L048": [
      "en",
      "06",
      1833,
      1
    ],
    "L049": [
      "en",
      "06",
      1838,
      1
    ],
    "L050": [
      "en",
      "06",
      1869,
      0
    ],
    "L051": [
      "en",
      "06",
      1963,
      5
    ],
    "L052": [
      "en",
      "06",
      2115,
      1
    ],
    "L053": [
      "en",
      "06",
      2130,
      2
    ],
    "L054": [
      "en",
      "07",
      133,
      0
    ],
    "L055": [
      "en",
      "07",
      212,
      1
    ],
    "L056": [
      "en",
      "07",
      268,
      1
    ],
    "L057": [
      "en",
      "07",
      424,
      5
    ],
    "L058": [
      "en",
      "07",
      603,
      1
    ],
    "L059": [
      "en",
      "07",
      635,
      2
    ],
    "L060": [
      "en",
      "10",
      62,
      3
    ],
    "L061": [
      "en",
      "10",
      66,
      0
    ],
    "L062": [
      "en",
      "10",
      93,
      1
    ],
    "L063": [
      "en",
      "10",
      305,
      0
    ],
    "L064": [
      "en",
      "10",
      359,
      0
    ],
    "L065": [
      "en",
      "10",
      543,
      0
    ],
    "L066": [
      "en",
      "10",
      608,
      0
    ],
    "L067": [
      "en",
      "10",
      630,
      3
    ],
    "L068": [
      "en",
      "10",
      687,
      4
    ],
    "L069": [
      "en",
      "10",
      1142,
      2
    ],
    "L070": [
      "en",
      "10",
      1295,
      0
    ],
    "L071": [
      "en",
      "10",
      1309,
      0
    ],
    "L072": [
      "en",
      "10",
      1423,
      0
    ],
    "L073": [
      "en",
      "10",
      2936,
      0
    ],
    "L074": [
      "en",
      "10",
      3478,
      0
    ],
    "L075": [
      "en",
      "10",
      3500,
      2
    ],
    "L076": [
      "en",
      "10",
      3793,
      2
    ],
    "L077": [
      "en",
      "10",
      3990,
      0
    ],
    "L078": [
      "en",
      "10",
      4083,
      2
    ],
    "L079": [
      "en",
      "10",
      4210,
      0
    ],
    "L080": [
      "en",
      "10",
      4296,
      0
    ],
    "L081": [
      "en",
      "10",
      4577,
      1
    ],
    "L082": [
      "en",
      "10",
      5128,
      0
    ],
    "L083": [
      "en",
      "10",
      5526,
      0
    ],
    "L084": [
      "en",
      "27",
      41,
      0
    ],
    "L085": [
      "en",
      "27",
      117,
      1
    ],
    "L086": [
      "en",
      "27",
      164,
      1
    ],
    "L087": [
      "en",
      "27",
      383,
      1
    ],
    "L088": [
      "en",
      "27",
      551,
      3
    ],
    "L089": [
      "en",
      "27",
      630,
      0
    ],
    "L090": [
      "en",
      "30",
      40,
      0
    ],
    "L091": [
      "en",
      "30",
      838,
      0
    ],
    "L092": [
      "en",
      "30",
      927,
      0
    ],
    "L093": [
      "en",
      "30",
      1539,
      0
    ],
    "L094": [
      "en",
      "30",
      1707,
      0
    ],
    "L095": [
      "en",
      "30",
      1979,
      0
    ],
    "L096": [
      "en",
      "30",
      2781,
      0
    ],
    "L097": [
      "en",
      "30",
      3354,
      0
    ],
    "L098": [
      "en",
      "30",
      3381,
      0
    ],
    "L099": [
      "en",
      "30",
      3394,
      0
    ],
    "L100": [
      "en",
      "34",
      31,
      0
    ],
    "L101": [
      "en",
      "34",
      474,
      0
    ],
    "L102": [
      "en",
      "34",
      1475,
      0
    ],
    "L103": [
      "en",
      "35",
      430,
      0
    ],
    "L104": [
      "en",
      "35",
      1177,
      0
    ],
    "L105": [
      "en",
      "35",
      1209,
      0
    ],
    "L106": [
      "en",
      "35",
      1216,
      0
    ],
    "L107": [
      "en",
      "35",
      2499,
      0
    ],
    "L108": [
      "en",
      "35",
      3587,
      0
    ],
    "L109": [
      "en",
      "35",
      3895,
      0
    ],
    "L110": [
      "en",
      "35",
      4546,
      0
    ],
    "L111": [
      "en",
      "35",
      5201,
      0
    ],
    "L112": [
      "en",
      "35",
      5253,
      0
    ],
    "L113": [
      "en",
      "35",
      6548,
      0
    ],
    "L114": [
      "en",
      "35",
      6845,
      0
    ],
    "L115": [
      "en",
      "35",
      7365,
      0
    ],
    "L116": [
      "en",
      "35",
      7986,
      0
    ],
    "L117": [
      "en",
      "35",
      8460,
      0
    ],
    "L118": [
      "en",
      "35",
      8568,
      0
    ],
    "L119": [
      "en",
      "35",
      9328,
      0
    ],
    "L120": [
      "en",
      "35",
      9335,
      0
    ],
    "L121": [
      "en",
      "35",
      9481,
      0
    ],
    "L122": [
      "en",
      "35",
      9559,
      0
    ],
    "L123": [
      "en",
      "35",
      11136,
      0
    ],
    "L124": [
      "en",
      "35",
      11766,
      0
    ],
    "L125": [
      "en",
      "35",
      12695,
      0
    ],
    "L126": [
      "en",
      "35",
      13794,
      0
    ],
    "L127": [
      "en",
      "35",
      14330,
      0
    ],
    "L128": [
      "en",
      "35",
      14577,
      0
    ],
    "L129": [
      "en",
      "35",
      15000,
      0
    ],
    "L130": [
      "en",
      "35",
      15421,
      0
    ],
    "L131": [
      "en",
      "47",
      102,
      0
    ],
    "L132": [
      "en",
      "47",
      385,
      0
    ],
    "L133": [
      "en",
      "47",
      533,
      0
    ],
    "L134": [
      "en",
      "47",
      558,
      0
    ],
    "L135": [
      "en",
      "47",
      1065,
      0
    ],
    "L136": [
      "en",
      "47",
      1133,
      0
    ],
    "L137": [
      "en",
      "47",
      1631,
      0
    ],
    "L138": [
      "en",
      "47",
      1727,
      0
    ],
    "L139": [
      "en",
      "47",
      1958,
      0
    ],
    "L140": [
      "en",
      "47",
      3211,
      0
    ],
    "L141": [
      "en",
      "47",
      3381,
      0
    ],
    "L142": [
      "en",
      "48",
      456,
      0
    ],
    "L143": [
      "en",
      "48",
      486,
      0
    ],
    "L144": [
      "en",
      "48",
      857,
      0
    ],
    "L145": [
      "en",
      "48",
      1492,
      0
    ],
    "L146": [
      "en",
      "48",
      1567,
      0
    ],
    "L147": [
      "en",
      "50",
      186,
      0
    ],
    "L148": [
      "en",
      "50",
      485,
      0
    ],
    "L149": [
      "en",
      "50",
      632,
      0
    ],
    "L150": [
      "en",
      "50",
      799,
      0
    ],
    "L151": [
      "en",
      "51",
      95,
      0
    ],
    "L152": [
      "en",
      "51",
      738,
      0
    ],
    "L153": [
      "en",
      "51",
      1065,
      0
    ],
    "L154": [
      "en",
      "51",
      1862,
      0
    ],
    "L155": [
      "en",
      "51",
      2070,
      0
    ],
    "L156": [
      "en",
      "51",
      2363,
      0
    ],
    "L157": [
      "en",
      "51",
      2461,
      0
    ],
    "L158": [
      "en",
      "51",
      2566,
      0
    ],
    "L159": [
      "en",
      "51",
      2730,
      0
    ],
    "L160": [
      "en",
      "51",
      4489,
      0
    ],
    "L161": [
      "en",
      "51",
      4523,
      0
    ],
    "L162": [
      "en",
      "51",
      4771,
      0
    ],
    "L163": [
      "en",
      "51",
      4867,
      0
    ],
    "L164": [
      "en",
      "51",
      4927,
      0
    ],
    "L165": [
      "en",
      "51",
      5477,
      0
    ],
    "L166": [
      "en",
      "51",
      5589,
      0
    ],
    "L167": [
      "en",
      "51",
      6169,
      0
    ],
    "L168": [
      "en",
      "51",
      6219,
      0
    ],
    "L169": [
      "en",
      "51",
      6241,
      0
    ],
    "L170": [
      "en",
      "51",
      6656,
      0
    ],
    "L171": [
      "en",
      "51",
      7017,
      0
    ],
    "L172": [
      "en",
      "51",
      7957,
      0
    ],
    "L173": [
      "en",
      "51",
      8523,
      0
    ],
    "L174": [
      "en",
      "51",
      9223,
      0
    ],
    "L175": [
      "en",
      "52",
      113,
      0
    ],
    "L176": [
      "en",
      "52",
      460,
      0
    ],
    "L177": [
      "en",
      "52",
      1198,
      0
    ],
    "L178": [
      "en",
      "52",
      1721,
      0
    ],
    "L179": [
      "en",
      "52",
      2440,
      0
    ],
    "L180": [
      "en",
      "52",
      2540,
      0
    ],
    "L181": [
      "en",
      "52",
      2613,
      0
    ],
    "L182": [
      "en",
      "52",
      3315,
      0
    ],
    "L183": [
      "en",
      "52",
      3354,
      0
    ],
    "L184": [
      "en",
      "52",
      3465,
      0
    ],
    "L185": [
      "en",
      "52",
      3843,
      0
    ],
    "L186": [
      "en",
      "52",
      3903,
      0
    ],
    "L187": [
      "en",
      "52",
      4147,
      0
    ],
    "L188": [
      "en",
      "52",
      4151,
      0
    ],
    "L189": [
      "en",
      "52",
      4528,
      0
    ],
    "L190": [
      "en",
      "52",
      4675,
      0
    ],
    "L191": [
      "en",
      "52",
      5724,
      0
    ],
    "L192": [
      "en",
      "52",
      5910,
      0
    ],
    "L193": [
      "en",
      "52",
      6074,
      0
    ],
    "L194": [
      "en",
      "52",
      6479,
      0
    ],
    "L195": [
      "en",
      "52",
      6480,
      0
    ],
    "L196": [
      "en",
      "52",
      7429,
      0
    ],
    "L197": [
      "en",
      "52",
      7650,
      0
    ],
    "L198": [
      "en",
      "52",
      7652,
      0
    ],
    "L199": [
      "en",
      "52",
      7800,
      0
    ],
    "L200": [
      "en",
      "52",
      8009,
      0
    ],
    "L201": [
      "en",
      "52",
      8329,
      0
    ],
    "L202": [
      "en",
      "52",
      8379,
      0
    ],
    "L203": [
      "en",
      "52",
      8486,
      0
    ],
    "L204": [
      "en",
      "52",
      8520,
      0
    ],
    "L205": [
      "en",
      "52",
      9845,
      0
    ],
    "L206": [
      "en",
      "52",
      10013,
      0
    ],
    "L207": [
      "en",
      "52",
      11083,
      0
    ],
    "L208": [
      "en",
      "52",
      13274,
      0
    ],
    "L209": [
      "en",
      "52",
      13679,
      0
    ],
    "L210": [
      "en",
      "52",
      13792,
      0
    ],
    "L211": [
      "en",
      "52",
      14038,
      0
    ],
    "L212": [
      "en",
      "52",
      14118,
      0
    ],
    "L213": [
      "en",
      "52",
      14295,
      0
    ],
    "L214": [
      "en",
      "52",
      14386,
      0
    ],
    "L215": [
      "en",
      "52",
      14630,
      0
    ],
    "L216": [
      "en",
      "52",
      14979,
      0
    ],
    "L217": [
      "en",
      "52",
      15123,
      0
    ],
    "L218": [
      "en",
      "52",
      16005,
      0
    ],
    "L219": [
      "en",
      "52",
      16288,
      0
    ],
    "L220": [
      "en",
      "52",
      16926,
      0
    ],
    "L221": [
      "en",
      "52",
      17042,
      0
    ],
    "L222": [
      "en",
      "52",
      17312,
      0
    ],
    "L223": [
      "en",
      "52",
      18405,
      0
    ],
    "L224": [
      "en",
      "52",
      18430,
      0
    ],
    "L225": [
      "en",
      "52",
      18729,
      0
    ],
    "L226": [
      "en",
      "52",
      19513,
      0
    ],
    "L227": [
      "en",
      "52",
      19774,
      0
    ],
    "L228": [
      "en",
      "52",
      20521,
      0
    ],
    "L229": [
      "en",
      "52",
      20916,
      0
    ],
    "L230": [
      "en",
      "52",
      21210,
      0
    ],
    "L231": [
      "en",
      "52",
      21604,
      0
    ],
    "L232": [
      "en",
      "52",
      22165,
      0
    ],
    "L233": [
      "en",
      "52",
      22178,
      0
    ],
    "L234": [
      "en",
      "59",
      785,
      0
    ],
    "L235": [
      "en",
      "59",
      1193,
      0
    ],
    "L236": [
      "en",
      "59",
      1252,
      0
    ],
    "L237": [
      "en",
      "60",
      146,
      0
    ],
    "L238": [
      "en",
      "60",
      451,
      0
    ],
    "L239": [
      "en",
      "60",
      1632,
      0
    ],
    "L240": [
      "en",
      "60",
      2192,
      0
    ],
    "L241": [
      "en",
      "60",
      2360,
      0
    ],
    "L242": [
      "en",
      "60",
      2720,
      0
    ],
    "L243": [
      "en",
      "60",
      2928,
      0
    ],
    "L244": [
      "en",
      "60",
      3297,
      0
    ],
    "L245": [
      "en",
      "60",
      3332,
      0
    ],
    "L246": [
      "en",
      "60",
      3508,
      0
    ],
    "L247": [
      "en",
      "60",
      5047,
      0
    ],
    "L248": [
      "en",
      "60",
      5048,
      0
    ],
    "L249": [
      "en",
      "60",
      5300,
      0
    ],
    "L250": [
      "en",
      "62",
      160,
      0
    ],
    "L251": [
      "en",
      "62",
      443,
      0
    ],
    "L252": [
      "en",
      "62",
      453,
      0
    ],
    "L253": [
      "en",
      "62",
      692,
      0
    ],
    "L254": [
      "en",
      "62",
      856,
      0
    ],
    "L255": [
      "en",
      "62",
      1270,
      0
    ],
    "L256": [
      "en",
      "62",
      1503,
      0
    ],
    "L257": [
      "en",
      "62",
      2125,
      0
    ],
    "L258": [
      "en",
      "62",
      2748,
      0
    ],
    "L259": [
      "en",
      "62",
      2800,
      0
    ],
    "L260": [
      "en",
      "62",
      3506,
      0
    ],
    "L261": [
      "en",
      "62",
      4322,
      0
    ],
    "L262": [
      "en",
      "62",
      4776,
      0
    ],
    "L263": [
      "en",
      "62",
      5407,
      0
    ],
    "L264": [
      "en",
      "62",
      6493,
      0
    ],
    "L265": [
      "en",
      "62",
      6598,
      0
    ],
    "L266": [
      "en",
      "62",
      7150,
      0
    ],
    "L267": [
      "en",
      "62",
      7191,
      0
    ],
    "L268": [
      "en",
      "62",
      7339,
      0
    ],
    "L269": [
      "en",
      "62",
      7408,
      0
    ],
    "L270": [
      "en",
      "62",
      7733,
      0
    ],
    "L271": [
      "en",
      "62",
      8025,
      0
    ],
    "L272": [
      "en",
      "62",
      8494,
      0
    ],
    "L273": [
      "en",
      "63",
      43,
      0
    ],
    "L274": [
      "en",
      "63",
      611,
      0
    ],
    "L275": [
      "en",
      "63",
      868,
      0
    ],
    "L276": [
      "en",
      "63",
      876,
      0
    ],
    "L277": [
      "en",
      "63",
      1477,
      0
    ],
    "L278": [
      "en",
      "63",
      1593,
      0
    ],
    "L279": [
      "en",
      "63",
      2428,
      0
    ],
    "L280": [
      "en",
      "63",
      2706,
      0
    ],
    "L281": [
      "en",
      "63",
      2840,
      0
    ],
    "L282": [
      "en",
      "63",
      3291,
      0
    ],
    "L283": [
      "en",
      "63",
      3509,
      0
    ],
    "L284": [
      "en",
      "63",
      3890,
      0
    ],
    "L285": [
      "en",
      "63",
      5431,
      0
    ],
    "L286": [
      "en",
      "63",
      5964,
      0
    ],
    "L287": [
      "en",
      "63",
      6270,
      0
    ],
    "L288": [
      "en",
      "63",
      6373,
      0
    ],
    "L289": [
      "en",
      "63",
      6748,
      0
    ],
    "L290": [
      "en",
      "63",
      6869,
      0
    ],
    "L291": [
      "en",
      "63",
      7619,
      0
    ],
    "L292": [
      "en",
      "63",
      8562,
      0
    ],
    "L293": [
      "en",
      "63",
      8693,
      0
    ],
    "L294": [
      "en",
      "63",
      9662,
      0
    ],
    "L295": [
      "en",
      "63",
      9884,
      0
    ],
    "L296": [
      "en",
      "63",
      10286,
      0
    ],
    "L297": [
      "en",
      "63",
      10434,
      0
    ],
    "L298": [
      "en",
      "63",
      10510,
      0
    ],
    "L299": [
      "en",
      "63",
      10815,
      0
    ],
    "L300": [
      "en",
      "63",
      11836,
      0
    ],
    "L301": [
      "en",
      "63",
      11943,
      0
    ],
    "L302": [
      "en",
      "63",
      12461,
      0
    ],
    "L303": [
      "en",
      "63",
      12475,
      0
    ],
    "L304": [
      "en",
      "63",
      13374,
      0
    ],
    "L305": [
      "en",
      "63",
      13604,
      0
    ],
    "L306": [
      "en",
      "63",
      13691,
      0
    ],
    "L307": [
      "en",
      "63",
      13743,
      0
    ],
    "L308": [
      "en",
      "63",
      14472,
      0
    ],
    "L309": [
      "en",
      "63",
      15224,
      0
    ],
    "L310": [
      "en",
      "63",
      15698,
      0
    ],
    "L311": [
      "en",
      "63",
      15760,
      0
    ],
    "L312": [
      "en",
      "63",
      15786,
      0
    ],
    "L313": [
      "en",
      "63",
      15979,
      0
    ],
    "L314": [
      "en",
      "63",
      16848,
      0
    ],
    "L315": [
      "en",
      "63",
      17002,
      0
    ],
    "L316": [
      "en",
      "63",
      17317,
      0
    ],
    "L317": [
      "en",
      "63",
      17318,
      0
    ],
    "L318": [
      "en",
      "63",
      17690,
      0
    ],
    "L319": [
      "en",
      "63",
      19369,
      0
    ],
    "L320": [
      "en",
      "63",
      20338,
      0
    ],
    "L321": [
      "en",
      "63",
      20390,
      0
    ],
    "L322": [
      "en",
      "63",
      20877,
      0
    ],
    "L323": [
      "en",
      "63",
      20949,
      0
    ],
    "L324": [
      "en",
      "63",
      21305,
      0
    ],
    "L325": [
      "en",
      "63",
      21422,
      0
    ],
    "L326": [
      "en",
      "63",
      21507,
      0
    ],
    "L327": [
      "en",
      "63",
      22003,
      0
    ],
    "L328": [
      "en",
      "63",
      22536,
      0
    ],
    "L329": [
      "en",
      "63",
      22775,
      0
    ],
    "L330": [
      "en",
      "63",
      24225,
      0
    ],
    "L331": [
      "en",
      "63",
      24362,
      0
    ],
    "L332": [
      "en",
      "64",
      32,
      0
    ],
    "L333": [
      "en",
      "64",
      1107,
      0
    ],
    "L334": [
      "en",
      "64",
      1330,
      0
    ],
    "L335": [
      "en",
      "64",
      1531,
      0
    ],
    "L336": [
      "en",
      "64",
      1730,
      0
    ],
    "L337": [
      "en",
      "64",
      1808,
      0
    ],
    "L338": [
      "en",
      "64",
      1969,
      0
    ],
    "L339": [
      "en",
      "64",
      2508,
      0
    ],
    "L340": [
      "en",
      "64",
      3070,
      0
    ],
    "L341": [
      "en",
      "64",
      3764,
      0
    ],
    "L342": [
      "en",
      "64",
      4056,
      0
    ],
    "L343": [
      "en",
      "64",
      4222,
      0
    ],
    "L344": [
      "en",
      "64",
      4458,
      0
    ],
    "L345": [
      "en",
      "64",
      4864,
      0
    ],
    "L346": [
      "en",
      "64",
      4960,
      0
    ],
    "L347": [
      "en",
      "64",
      5073,
      0
    ],
    "L348": [
      "en",
      "64",
      5267,
      0
    ],
    "L349": [
      "en",
      "64",
      5944,
      0
    ],
    "L350": [
      "en",
      "64",
      7283,
      0
    ],
    "L351": [
      "en",
      "64",
      7330,
      0
    ],
    "L352": [
      "en",
      "64",
      7504,
      0
    ],
    "L353": [
      "en",
      "64",
      8243,
      0
    ],
    "L354": [
      "en",
      "64",
      8724,
      0
    ],
    "L355": [
      "en",
      "64",
      9634,
      0
    ],
    "L356": [
      "en",
      "64",
      11005,
      0
    ],
    "L357": [
      "en",
      "64",
      11097,
      0
    ],
    "L358": [
      "en",
      "64",
      12079,
      0
    ],
    "L359": [
      "en",
      "64",
      12579,
      0
    ],
    "L360": [
      "en",
      "64",
      12894,
      0
    ],
    "L361": [
      "en",
      "64",
      13246,
      0
    ],
    "L362": [
      "en",
      "64",
      13783,
      0
    ],
    "L363": [
      "en",
      "64",
      14208,
      0
    ],
    "L364": [
      "en",
      "64",
      14361,
      0
    ],
    "L365": [
      "en",
      "64",
      14520,
      0
    ],
    "L366": [
      "en",
      "64",
      16469,
      0
    ],
    "L367": [
      "en",
      "64",
      16866,
      0
    ],
    "L368": [
      "en",
      "64",
      17329,
      0
    ],
    "L369": [
      "en",
      "64",
      17473,
      0
    ],
    "L370": [
      "en",
      "64",
      18033,
      0
    ],
    "L371": [
      "en",
      "64",
      18188,
      0
    ],
    "L372": [
      "en",
      "64",
      19257,
      0
    ],
    "L373": [
      "en",
      "64",
      19296,
      0
    ],
    "L374": [
      "en",
      "64",
      20340,
      0
    ],
    "L375": [
      "en",
      "64",
      21064,
      0
    ],
    "L376": [
      "en",
      "64",
      21155,
      0
    ],
    "L377": [
      "en",
      "64",
      22121,
      0
    ],
    "L378": [
      "en",
      "64",
      22552,
      0
    ],
    "L379": [
      "en",
      "64",
      22705,
      0
    ],
    "L380": [
      "en",
      "64",
      22813,
      0
    ],
    "L381": [
      "en",
      "64",
      22982,
      0
    ],
    "L382": [
      "en",
      "64",
      23268,
      0
    ],
    "L383": [
      "en",
      "64",
      23343,
      0
    ],
    "L384": [
      "en",
      "64",
      23354,
      0
    ],
    "L385": [
      "en",
      "64",
      23959,
      0
    ],
    "L386": [
      "en",
      "64",
      24013,
      0
    ],
    "L387": [
      "en",
      "64",
      24598,
      0
    ],
    "L388": [
      "en",
      "64",
      25134,
      0
    ],
    "L389": [
      "en",
      "64",
      25191,
      0
    ],
    "L390": [
      "en",
      "64",
      25848,
      0
    ],
    "L391": [
      "en",
      "64",
      25876,
      0
    ],
    "L392": [
      "en",
      "64",
      26375,
      0
    ],
    "L393": [
      "en",
      "64",
      27925,
      0
    ],
    "L394": [
      "en",
      "64",
      28517,
      0
    ],
    "L395": [
      "en",
      "64",
      28572,
      0
    ],
    "L396": [
      "en",
      "64",
      29067,
      0
    ],
    "L397": [
      "en",
      "64",
      29266,
      0
    ],
    "L398": [
      "en",
      "64",
      29713,
      0
    ],
    "L399": [
      "en",
      "64",
      29715,
      0
    ],
    "L400": [
      "en",
      "64",
      29782,
      0
    ],
    "L401": [
      "en",
      "64",
      29811,
      0
    ],
    "L402": [
      "en",
      "64",
      30011,
      0
    ],
    "L403": [
      "en",
      "64",
      30081,
      0
    ],
    "L404": [
      "en",
      "64",
      30135,
      0
    ],
    "L405": [
      "en",
      "64",
      30187,
      0
    ],
    "L406": [
      "en",
      "64",
      30362,
      0
    ],
    "L407": [
      "en",
      "64",
      30427,
      0
    ],
    "L408": [
      "en",
      "64",
      30980,
      0
    ],
    "L409": [
      "en",
      "64",
      31561,
      0
    ],
    "L410": [
      "en",
      "64",
      32071,
      0
    ],
    "L411": [
      "en",
      "64",
      33681,
      0
    ],
    "L412": [
      "en",
      "64",
      34328,
      0
    ],
    "L413": [
      "en",
      "64",
      34762,
      0
    ],
    "L414": [
      "en",
      "64",
      34882,
      0
    ],
    "L415": [
      "en",
      "64",
      35077,
      0
    ],
    "L416": [
      "en",
      "64",
      35201,
      0
    ],
    "L417": [
      "en",
      "64",
      35848,
      0
    ],
    "L418": [
      "en",
      "64",
      35878,
      0
    ],
    "L419": [
      "en",
      "64",
      36234,
      0
    ],
    "L420": [
      "en",
      "64",
      36416,
      0
    ],
    "L421": [
      "en",
      "64",
      36672,
      0
    ],
    "L422": [
      "en",
      "64",
      38106,
      0
    ],
    "L423": [
      "en",
      "64",
      38131,
      0
    ],
    "L424": [
      "en",
      "64",
      38196,
      0
    ],
    "L425": [
      "en",
      "64",
      38250,
      0
    ],
    "L426": [
      "en",
      "64",
      38268,
      0
    ],
    "L427": [
      "en",
      "64",
      38307,
      0
    ],
    "L428": [
      "en",
      "64",
      39121,
      0
    ],
    "L429": [
      "en",
      "64",
      39175,
      0
    ],
    "L430": [
      "en",
      "64",
      39365,
      0
    ],
    "L431": [
      "en",
      "65",
      136,
      0
    ],
    "L432": [
      "en",
      "65",
      478,
      0
    ],
    "L433": [
      "en",
      "66",
      180,
      0
    ],
    "L434": [
      "en",
      "66",
      513,
      0
    ],
    "L435": [
      "en",
      "66",
      518,
      0
    ],
    "L436": [
      "en",
      "66",
      922,
      0
    ],
    "L437": [
      "en",
      "66",
      1008,
      0
    ],
    "L438": [
      "en",
      "66",
      1442,
      0
    ],
    "L439": [
      "en",
      "66",
      1781,
      0
    ],
    "L440": [
      "en",
      "66",
      2729,
      0
    ],
    "L441": [
      "en",
      "66",
      3406,
      0
    ],
    "L442": [
      "en",
      "66",
      3673,
      0
    ],
    "L443": [
      "en",
      "66",
      3739,
      0
    ],
    "L444": [
      "en",
      "66",
      4337,
      0
    ],
    "L445": [
      "en",
      "66",
      4480,
      0
    ],
    "L446": [
      "en",
      "66",
      4634,
      0
    ],
    "L447": [
      "en",
      "66",
      5190,
      0
    ],
    "L448": [
      "en",
      "66",
      6172,
      0
    ],
    "L449": [
      "en",
      "66",
      6185,
      0
    ],
    "L450": [
      "en",
      "66",
      7398,
      0
    ],
    "L451": [
      "en",
      "66",
      7824,
      0
    ],
    "L452": [
      "en",
      "66",
      7966,
      0
    ],
    "L453": [
      "en",
      "67",
      60,
      0
    ],
    "L454": [
      "en",
      "67",
      472,
      0
    ],
    "L455": [
      "en",
      "67",
      589,
      0
    ],
    "L456": [
      "en",
      "67",
      1473,
      0
    ],
    "L457": [
      "en",
      "68",
      295,
      0
    ],
    "L458": [
      "en",
      "68",
      459,
      0
    ],
    "L459": [
      "en",
      "68",
      604,
      0
    ],
    "L460": [
      "en",
      "69",
      32,
      0
    ],
    "L461": [
      "en",
      "69",
      345,
      0
    ],
    "L462": [
      "en",
      "70",
      127,
      0
    ],
    "L463": [
      "en",
      "70",
      201,
      0
    ],
    "L464": [
      "en",
      "70",
      661,
      0
    ],
    "L465": [
      "en",
      "70",
      1507,
      0
    ],
    "L466": [
      "en",
      "70",
      1889,
      0
    ],
    "L467": [
      "en",
      "70",
      3050,
      0
    ],
    "L468": [
      "en",
      "70",
      3324,
      0
    ],
    "L469": [
      "en",
      "70",
      3398,
      0
    ],
    "L470": [
      "en",
      "71",
      362,
      0
    ],
    "L471": [
      "en",
      "71",
      1094,
      0
    ],
    "L472": [
      "en",
      "71",
      1248,
      0
    ],
    "L473": [
      "en",
      "71",
      1762,
      0
    ],
    "L474": [
      "en",
      "71",
      2022,
      0
    ],
    "L475": [
      "en",
      "71",
      2482,
      0
    ],
    "L476": [
      "en",
      "71",
      2780,
      0
    ],
    "L477": [
      "en",
      "71",
      2813,
      0
    ],
    "L478": [
      "en",
      "71",
      3158,
      0
    ],
    "L479": [
      "en",
      "71",
      3290,
      0
    ],
    "L480": [
      "en",
      "71",
      3360,
      0
    ],
    "L481": [
      "en",
      "71",
      3448,
      0
    ],
    "L482": [
      "en",
      "71",
      3611,
      0
    ],
    "L483": [
      "en",
      "71",
      3935,
      0
    ],
    "L484": [
      "en",
      "71",
      4163,
      0
    ],
    "L485": [
      "en",
      "71",
      5163,
      0
    ],
    "L486": [
      "en",
      "71",
      5426,
      0
    ],
    "L487": [
      "en",
      "71",
      5455,
      0
    ],
    "L488": [
      "en",
      "71",
      6895,
      0
    ],
    "L489": [
      "en",
      "71",
      7784,
      0
    ]
  },
  "text_hash_by_key": {
    "L001": "f81118a4823abd4a",
    "L002": "cf6a81ca3e0b216b",
    "L003": "4cba6904030369f6",
    "L004": "eca5039cd0c183bf",
    "L005": "b74054856235c409",
    "L006": "bd7054ebcfe1a20b",
    "L007": "06fa99006b29621c",
    "L008": "2158d59fb05b1f3a",
    "L009": "0593b0feeac420a5",
    "L010": "e137ef8d32e0d243",
    "L011": "29a19532b1028332",
    "L012": "a6ce7995fadbc581",
    "L013": "3142b4d3478ffc15",
    "L014": "e6f1af848e93989d",
    "L015": "50a67b82580f7afc",
    "L016": "cda2805aefe85213",
    "L017": "c8cd49570a121d03",
    "L018": "29a3a23b2f4d8df2",
    "L019": "7e8265bd200ff394",
    "L020": "8ace8a11482134e4",
    "L021": "daca2addc4bc70fc",
    "L022": "09445065a65eb9d0",
    "L023": "7f73c0ac820d4146",
    "L024": "da4cd0573937477a",
    "L025": "b4f46727d0e50176",
    "L026": "8e27893c64c87336",
    "L027": "4965fe4d0f4a33c8",
    "L028": "c5f7226bed2bab12",
    "L029": "a804bc42ec63d3ed",
    "L030": "d4ed8a1c63846097",
    "L031": "e9c280030a5bf9ba",
    "L032": "e992ef9bb8a80c47",
    "L033": "43232c24d6bab807",
    "L034": "d0f713acf6e8cbe9",
    "L035": "626c10a7e51aee4b",
    "L036": "4307d3aaad71d54b",
    "L037": "caeff7ef5c19c511",
    "L038": "edf632fd6d9262fa",
    "L039": "5f1ad68a815abaff",
    "L040": "85aaa89e437b2471",
    "L041": "e080927c3fb01a31",
    "L042": "9fa77b01078375f5",
    "L043": "11ebcc6721e52779",
    "L044": "e09c88515c115b93",
    "L045": "fa51ce4703d28cf8",
    "L046": "30f7646b8fc14ba2",
    "L047": "9d3822363667ccea",
    "L048": "6e81cbf91ad0e042",
    "L049": "300019ac7bca64e8",
    "L050": "02cc020f791cdbd4",
    "L051": "c0b43fceb05d3547",
    "L052": "50baf2748d3a4573",
    "L053": "5ffedeceb7fb47f5",
    "L054": "037e2eb89654a225",
    "L055": "e0e3a71c7fc0cf6c",
    "L056": "8c4c4e3f93bf8a8a",
    "L057": "7907423adc6ebad3",
    "L058": "c6828bf4e32f6cbd",
    "L059": "a1aa9b3ddf6287de",
    "L060": "c25fcfb983eac895",
    "L061": "0a4a5e5a0bc60e0b",
    "L062": "73d8fba9e7d2a4ae",
    "L063": "1f92fc83eace68c7",
    "L064": "fb699ebcb92fc841",
    "L065": "b814cdd03ab82c3d",
    "L066": "465e8d9c058cecff",
    "L067": "23af3b0795b45d80",
    "L068": "6ee2bdf5295a16c2",
    "L069": "79b11c3516650191",
    "L070": "a016b7fa06563749",
    "L071": "e8209287d0b81929",
    "L072": "4d785c236b6774cb",
    "L073": "254ecb2e32bd06d4",
    "L074": "54c193768d02555c",
    "L075": "6518e8cc42120650",
    "L076": "91685c9ef3e9a52d",
    "L077": "e8209287d0b81929",
    "L078": "59bc01bf39d115b9",
    "L079": "dca55a5dd56f6472",
    "L080": "e8209287d0b81929",
    "L081": "dde2d8a2e5575dac",
    "L082": "ab0c2e5e23107d04",
    "L083": "81182e9c7000074f",
    "L084": "1badd39eb3e26a11",
    "L085": "56b67a18547c1cc2",
    "L086": "f554df6849fe31b5",
    "L087": "97441b63de2f945b",
    "L088": "b875ef6340e980a2",
    "L089": "2cdbb018a9cc06b2",
    "L090": "47e0ae67577fc04d",
    "L091": "292e7906973a8c1b",
    "L092": "6fee7de69d63a57b",
    "L093": "1e690b4ae50396aa",
    "L094": "9a55853e2cbb6e28",
    "L095": "dc50c3a17ada324e",
    "L096": "7d3eef39f0dcd57e",
    "L097": "f1734e7440cb47f2",
    "L098": "b8cd79dac9130487",
    "L099": "e132820ae3e75483",
    "L100": "f011748c99e8f603",
    "L101": "eb3833f70b5fe6f0",
    "L102": "35dbb3762cd5b11d",
    "L103": "0cae3fea8a659103",
    "L104": "25f6212b782cd3a1",
    "L105": "262b74f8dc1d3b4e",
    "L106": "1e040c05ade1329d",
    "L107": "4b02cf599a64cec3",
    "L108": "4ad54734a5942067",
    "L109": "38d5fcabfd86838b",
    "L110": "363a5ed290c34b9d",
    "L111": "843170953174e409",
    "L112": "bb2a967100d459cc",
    "L113": "0c655436b7cbf898",
    "L114": "45026d574a053d8e",
    "L115": "cf8c2c906df458a9",
    "L116": "e6165875f640d645",
    "L117": "ad6eb5cea5c8fcc4",
    "L118": "19ee0a532c4ef8dd",
    "L119": "143fc4bd9c4c5201",
    "L120": "ccb75c8f293e5b32",
    "L121": "15217e44368f9bd6",
    "L122": "35fe5fdfa8d7e58d",
    "L123": "cb8c82cccd76f09b",
    "L124": "dc174268c487777d",
    "L125": "1b2fe21ab804f35f",
    "L126": "09a15abe97df7094",
    "L127": "a7f56e069458e902",
    "L128": "ddb633d48a1593de",
    "L129": "1392579940f3d7d9",
    "L130": "681a999237070360",
    "L131": "7deeac131fe900cf",
    "L132": "6cfff2e43f2ca8e8",
    "L133": "82529ddb7091a03d",
    "L134": "91f6d3f64b9cfd7a",
    "L135": "6afada2c7cf0c995",
    "L136": "bf173da9220ba8db",
    "L137": "1e40c5328548a688",
    "L138": "5f9a2b795615ba6a",
    "L139": "5aa735a2b55980d9",
    "L140": "6aabae8e9649db1f",
    "L141": "e5b579e6485ae748",
    "L142": "8fb23667e64a97d5",
    "L143": "befbc12dc5149f92",
    "L144": "51eca7d46b704cee",
    "L145": "b5881c5b47ce0071",
    "L146": "5bdff815a43c6b56",
    "L147": "4dec2c877c882c0c",
    "L148": "fd40643ce661f5af",
    "L149": "57538cccbfb20786",
    "L150": "396c9664c59cb93d",
    "L151": "ad7ae6bc58376f3a",
    "L152": "7c1adcabff577c71",
    "L153": "db9a6eb1950e7832",
    "L154": "ce522a1d9f991135",
    "L155": "4d766662004a51d4",
    "L156": "ec34a5c67c829452",
    "L157": "8b78a84a3ae39d8b",
    "L158": "2c027084fde6e01b",
    "L159": "f3991ae2cfb86b9c",
    "L160": "6860d8437101e3da",
    "L161": "68e933363ea2337e",
    "L162": "bb65c54545d7d88a",
    "L163": "72c9f7430ca5604e",
    "L164": "f388d6476e1db66f",
    "L165": "4f894b35410ff907",
    "L166": "cc10af85c72f1778",
    "L167": "d8bcf5d5c1884a70",
    "L168": "43b9bbc2c67d6f16",
    "L169": "47c03147a6f206dc",
    "L170": "9282d454ff1429f0",
    "L171": "f061000c5d8bf8c0",
    "L172": "d4af140a1e84bc61",
    "L173": "652c898d3a005f16",
    "L174": "78be4b7bf4011fcc",
    "L175": "a1daf23bd0661afe",
    "L176": "db446e6b6753336d",
    "L177": "4a9bc6b9fa23ba93",
    "L178": "04d80f71588d4c4d",
    "L179": "f2ba63920b2891a1",
    "L180": "af901ec77ca4a8e9",
    "L181": "c83c07c08092a807",
    "L182": "335babd0020bc287",
    "L183": "b5e850555ad2fcfc",
    "L184": "c35a720b8e675dbf",
    "L185": "3a9ac108eb121719",
    "L186": "75eb65d2c5ca500b",
    "L187": "8d2484dc5df81ae2",
    "L188": "f7fcbff811064291",
    "L189": "70a5f87845f85f06",
    "L190": "0b0bf02433d3292c",
    "L191": "525c73b331e1211c",
    "L192": "8ea13780efb354cb",
    "L193": "dce1148aa0fe2f69",
    "L194": "3062037fee22a24e",
    "L195": "bc94aeacf2c675f7",
    "L196": "9a7434019f3d25cf",
    "L197": "04ab2fcba5aaa875",
    "L198": "00a894b2c4e7b04b",
    "L199": "e05d00524d1aeab3",
    "L200": "ecf19146369f8556",
    "L201": "2c1d09e99fba3226",
    "L202": "79ff5adb4a3be9fb",
    "L203": "ffdf0f7457236f3d",
    "L204": "1ab3c29df426bb13",
    "L205": "cc37288d08f9ad67",
    "L206": "06d77dea67292130",
    "L207": "d062458cbf08a550",
    "L208": "4110114dc6772a17",
    "L209": "ae9ab47c13d350fb",
    "L210": "de5d6d092b354a97",
    "L211": "93f003f977618025",
    "L212": "7e49f87802689164",
    "L213": "f62b79c540460f1b",
    "L214": "cd59206a8761bcff",
    "L215": "13a07b16f995862d",
    "L216": "7b981b4c2284a5cb",
    "L217": "b23bf18343838159",
    "L218": "b6f028ebee7c30e0",
    "L219": "a45af9827b2d36f1",
    "L220": "e468b47aaa7e6ea0",
    "L221": "30582cc5370b03a2",
    "L222": "3e7de26225533bf8",
    "L223": "dd1a803df75cd78f",
    "L224": "c8b24aaf25817f34",
    "L225": "b056113b01a5d825",
    "L226": "8788908da1c2b032",
    "L227": "5706ebb2cf8f037a",
    "L228": "4937415fd28e8067",
    "L229": "b6c6a8427cad9e46",
    "L230": "bc4b87d9298725ec",
    "L231": "1f751e1a00b1139b",
    "L232": "43d08516be07862d",
    "L233": "afdf2d68e3167269",
    "L234": "7d852fbcf744a081",
    "L235": "47bffdcf2e90ff08",
    "L236": "fd1143227e6edad7",
    "L237": "ff0b793ccfe37a49",
    "L238": "ca37132dc8ee8da7",
    "L239": "7855a51470ac15e4",
    "L240": "3fb680363bd7df26",
    "L241": "25b89648629e8b57",
    "L242": "15908779fb85cbb3",
    "L243": "dbf769911e7a55cc",
    "L244": "3dd1c79b14fc53c2",
    "L245": "2a367484fa2dff89",
    "L246": "26d354337a7dd881",
    "L247": "7b1f19a445c66611",
    "L248": "78cca5adebe0763f",
    "L249": "75d1d7e454bc25e4",
    "L250": "60d446cd7d41b066",
    "L251": "4718cd3e1451f31f",
    "L252": "9f0e805906e57c78",
    "L253": "79971e500e19302e",
    "L254": "f80ee45dcf57d2c9",
    "L255": "6bc5f02ff678dd88",
    "L256": "7d00a98318c39749",
    "L257": "44b9ccbaaf9ddbda",
    "L258": "7ea17a978638250d",
    "L259": "5ad486b62962e27d",
    "L260": "0a1b6a1fd19818e7",
    "L261": "8e311b39077fff33",
    "L262": "5627a58dd5a0da27",
    "L263": "dbe59e29322c00eb",
    "L264": "3d0d8d13764ddd6a",
    "L265": "5e56b62e7f1b83b3",
    "L266": "ab002a0e460fb11f",
    "L267": "504e8fb735613ec6",
    "L268": "3282ea86c7399ae5",
    "L269": "6a32caeec03e5be6",
    "L270": "ad5c1fd2ebed4977",
    "L271": "8ed22490948cd048",
    "L272": "16e95e0fb6917a90",
    "L273": "c0cd262a731e7962",
    "L274": "e2bb21f20123a34e",
    "L275": "3ee0941c31f05c65",
    "L276": "c46ab6c43275b0ea",
    "L277": "3b8b203a2f1fc108",
    "L278": "89d4478c63a94e59",
    "L279": "f5207affee2c2172",
    "L280": "45905852ea5c4f07",
    "L281": "1915f962c260be79",
    "L282": "c192c85c62338ce6",
    "L283": "4c3c0538c29d0511",
    "L284": "c3d39ba83d0d9633",
    "L285": "c45b8e5dc9c05cac",
    "L286": "5ed3cb7e9dffee7a",
    "L287": "6f890a23f09c5267",
    "L288": "e04c7dbb42d9ec3d",
    "L289": "fb87c077b62fd5e0",
    "L290": "01d8ad5d3d0619e7",
    "L291": "9032a0489e0cd981",
    "L292": "896e2b0181e4f7e3",
    "L293": "71bc6e0f3dbb227d",
    "L294": "9c256a380c81a85e",
    "L295": "8656bc08a00f4ec6",
    "L296": "227f87fe287748b7",
    "L297": "4c0812f7008358b4",
    "L298": "74c16a1f4a6ebd71",
    "L299": "5fde153d87fa9a31",
    "L300": "1745e83d6a34157c",
    "L301": "b3203ea78458d7dc",
    "L302": "91006402b59cdbef",
    "L303": "5730b77acc26e7e5",
    "L304": "003aac4130a1bdc2",
    "L305": "753bbbf9aefba414",
    "L306": "1055fdc2278f6988",
    "L307": "fa4c4a448713edbd",
    "L308": "291f46b4183f582a",
    "L309": "543f6044de13db06",
    "L310": "96a5507e44479231",
    "L311": "cdc13f893da7e314",
    "L312": "604da66a24c1d01d",
    "L313": "1f4a6e290e117b56",
    "L314": "a8a19c100e3f712e",
    "L315": "8aa2e985d17c48d3",
    "L316": "2b1db8c234d77cb3",
    "L317": "7baf76b685acab05",
    "L318": "c63c704ae2b024c4",
    "L319": "c17f5a1005717b4e",
    "L320": "c75befc64765c13e",
    "L321": "024d2738c416926c",
    "L322": "57e4819ad80679c3",
    "L323": "9c87752d74847b91",
    "L324": "8906d8399a4b9cbb",
    "L325": "33b5643b3dc3a853",
    "L326": "f7c09ba14db21258",
    "L327": "4ca5a0ea66530450",
    "L328": "5aeba7d491fbf523",
    "L329": "684acdbf62653c30",
    "L330": "7957d183133f1956",
    "L331": "96b09527d153eb33",
    "L332": "e391a3b2fc3a7dcf",
    "L333": "cd2626136892a3f5",
    "L334": "6d494a85a2246fe0",
    "L335": "01abaf25fce7c82e",
    "L336": "36dc0223adba524d",
    "L337": "ece8658e00ccdcba",
    "L338": "e8d4367dc6a5225e",
    "L339": "d4f1163cc3d54d8b",
    "L340": "52921fa8bd12570f",
    "L341": "10a8408417e666ab",
    "L342": "802c90f7adf2022a",
    "L343": "81a50b56a24fc939",
    "L344": "88912f96bae619ef",
    "L345": "15b791093a72232b",
    "L346": "518854f4056a6a6d",
    "L347": "a9916b4b8f6e3feb",
    "L348": "8a9760f793a4f373",
    "L349": "dbd8183cb6ece0b4",
    "L350": "3aa61a477b06441c",
    "L351": "51ecd124d7492a68",
    "L352": "ebd1ae61d11bbaec",
    "L353": "a7182856e9b27bda",
    "L354": "c2b5351c739e6ea3",
    "L355": "4e92abbfce69f4cd",
    "L356": "d5deaf354783beee",
    "L357": "1d4f9f9e1ee9e656",
    "L358": "670135e1c6196d20",
    "L359": "5c0b3836fe770c6f",
    "L360": "bbd4193cb01183c1",
    "L361": "fd4088970224545e",
    "L362": "8f667e9a6456a684",
    "L363": "875ddd7d8ba23165",
    "L364": "fe7f38e25d830541",
    "L365": "a0d2a3f05ad06710",
    "L366": "ed19de4b785e7761",
    "L367": "3294b9f4382fbd70",
    "L368": "50e282af836f7210",
    "L369": "ec403de91f0d3128",
    "L370": "92a090ac27baaffa",
    "L371": "1ca63ddaea942f34",
    "L372": "6424a42f31ce4b29",
    "L373": "f5899b7cbf6c4277",
    "L374": "c4efe0061fb726b5",
    "L375": "67784275727a83ed",
    "L376": "75612ec121100d9f",
    "L377": "e9c7f8fecfdf17fd",
    "L378": "7a716544dcbb4779",
    "L379": "3c0daa6e85b7ecae",
    "L380": "7d4faf8e62ab7c5b",
    "L381": "68ac46151271df98",
    "L382": "3702a71034f2fb15",
    "L383": "fb990e4d463bbafa",
    "L384": "fed1447906bfe432",
    "L385": "42a672ffece3d8a3",
    "L386": "0d45c227656a1f3e",
    "L387": "3ae79f5f535e55f2",
    "L388": "529ef9c247866b94",
    "L389": "76c32607a2741a3f",
    "L390": "2553a3e81afdf0d3",
    "L391": "02675c9e0d3fd5c9",
    "L392": "74286e28abf59292",
    "L393": "727190d1f12ad6e6",
    "L394": "ef02ca4fa2e0a8bf",
    "L395": "f2ad99a44a836a1c",
    "L396": "120172f6e18220be",
    "L397": "9854543d04e3f67b",
    "L398": "53473d94a5caa4da",
    "L399": "ed2aadcf6105973d",
    "L400": "cf4f1d7e08b517c3",
    "L401": "200aadf2be737e14",
    "L402": "f5f2037d325673c9",
    "L403": "7fb6db2bafb96ae7",
    "L404": "fb290515f7008d8e",
    "L405": "759d360c2963e337",
    "L406": "06645404cbdb7c8b",
    "L407": "727190d1f12ad6e6",
    "L408": "a229e3319f571ee9",
    "L409": "36743fc08ba7c868",
    "L410": "57236e73cc6b55e3",
    "L411": "5ce5198f470ea91a",
    "L412": "83ef50f50a0fba84",
    "L413": "1d0b24b9347e45eb",
    "L414": "d4a7a678dff1707b",
    "L415": "eb90f2720478615f",
    "L416": "185970004c3c21cf",
    "L417": "e4cc5fc7ede61e76",
    "L418": "5f5d55d9efcb7791",
    "L419": "ceb11eae97e31677",
    "L420": "a49ae1abad510f95",
    "L421": "fe8d4e4569ec3d81",
    "L422": "a064f362c6e36e4e",
    "L423": "bac47f211c97eb41",
    "L424": "5b0ff77d0c37043f",
    "L425": "7548f330f3d04ebe",
    "L426": "7df6510bc8f82ce1",
    "L427": "cedb4da0bae03c3a",
    "L428": "3192642309bc59a5",
    "L429": "d1fe33616dfedb5f",
    "L430": "976976ab910e4feb",
    "L431": "098209d85274c67e",
    "L432": "92ae9e44a3c7d04d",
    "L433": "cde350435008e087",
    "L434": "035df7958296f90c",
    "L435": "3bd4f87cd7e0f22f",
    "L436": "bbb504b7432fab30",
    "L437": "8a6e8da2a0a85be9",
    "L438": "c06ab68a5fafe48d",
    "L439": "620ba81614e39687",
    "L440": "91c7c3f17ffd8af3",
    "L441": "b2b5aca25f32f53a",
    "L442": "b23cd43cfa18a21d",
    "L443": "380b53be3cb0ef0e",
    "L444": "c5353dc8a0a3f7f9",
    "L445": "b9f03465b06f4f51",
    "L446": "a14bd68936d424ec",
    "L447": "c8fa30ea3a3b0e03",
    "L448": "9328d4d348baff0d",
    "L449": "3c950a60dcd923e8",
    "L450": "200120bf901a132f",
    "L451": "e4479735bde27a0b",
    "L452": "899bda9ddf0be755",
    "L453": "503e8c92b3e1a194",
    "L454": "aefb8ede4acffe94",
    "L455": "0402149599633963",
    "L456": "ff2b71bdbe08a0bd",
    "L457": "e7264d98033aedc3",
    "L458": "f7efc7a0788b71ac",
    "L459": "57b86bba6b622197",
    "L460": "920d2874f9561ea4",
    "L461": "b66dc243462c41f0",
    "L462": "4ea40897d79f13ac",
    "L463": "547b8de7ed2181a0",
    "L464": "5c8a67a72756a3c2",
    "L465": "67b9529a6f2026d9",
    "L466": "744547431dd6d82f",
    "L467": "325e93cbf48dc726",
    "L468": "3d6197a771d59184",
    "L469": "68b2dc42dd95cdd4",
    "L470": "582c03daa4ef42a9",
    "L471": "64c298b0daaf9f5a",
    "L472": "19cfa6ff2ca34490",
    "L473": "cb9d1099218f21dc",
    "L474": "7c9796e42a514e02",
    "L475": "cbce0c6b0f7ae025",
    "L476": "1e2bc33833b29922",
    "L477": "484f8e85ce804045",
    "L478": "e87a4e70c40201d3",
    "L479": "3d11dc7c6b7050ae",
    "L480": "d73f145d4d2f2ffa",
    "L481": "8c53977ac97dd271",
    "L482": "a1d64c0f8a917152",
    "L483": "4015d7b0e017952f",
    "L484": "d800325ce015f368",
    "L485": "7d43775ed98aeebe",
    "L486": "49bfcd51c5efc608",
    "L487": "276a327dc3cf9905",
    "L488": "1626dfe55c33161d",
    "L489": "6efe0b26b083684d"
  },
  "item_by_key": {
    "L001": "b01-r0",
    "L002": "b01-r1",
    "L003": "b01-r2",
    "L004": "b01-r3",
    "L005": "b01-r4",
    "L006": "b01-r5",
    "L007": "b01-r6",
    "L008": "b01-r7",
    "L009": "b01-r8",
    "L010": "b01-r9",
    "L011": "b01-r10",
    "L012": "b01-r11",
    "L013": "b01-r12",
    "L014": "b01-r13",
    "L015": "b01-r14s0",
    "L016": "b01-r14s1",
    "L017": "b01-r14s2",
    "L018": "b01-r14s3",
    "L019": "b01-r14s4",
    "L020": "b02-r0",
    "L021": "b02-r0",
    "L022": "b02-r1",
    "L023": "b02-r2",
    "L024": "b02-r2",
    "L025": "b02-r3",
    "L026": "b02-r4",
    "L027": "b03-r0",
    "L028": "b03-r1",
    "L029": "b03-r2",
    "L030": "b03-r3",
    "L031": "b03-r4",
    "L032": "b03-r5",
    "L033": "b03-r6",
    "L034": "b03-r7",
    "L035": "b03-r8",
    "L036": "b04-r0",
    "L037": "b04-r1",
    "L038": "b04-r2",
    "L039": "b05-r0",
    "L040": "b05-r1",
    "L041": "b05-r2",
    "L042": "b06-r0",
    "L043": "b06-r1",
    "L044": "b06-r2",
    "L045": "b06-r3",
    "L046": "b06-r4",
    "L047": "b06-r5",
    "L048": "b06-r6",
    "L049": "b06-r6",
    "L050": "b06-r7",
    "L051": "b06-r8",
    "L052": "b06-r9",
    "L053": "b06-r9",
    "L054": "b07-r0",
    "L055": "b07-r1",
    "L056": "b07-r2",
    "L057": "b07-r3",
    "L058": "b07-r4",
    "L059": "b07-r5",
    "L060": "b10-r0",
    "L061": "b10-r0",
    "L062": "b10-r0",
    "L063": "b10-r1",
    "L064": "b10-r1",
    "L065": "b10-r2",
    "L066": "b10-r2",
    "L067": "b10-r2",
    "L068": "b10-r3s0",
    "L069": "b10-r3s1",
    "L070": "b10-r3s2",
    "L071": "b10-r3s2",
    "L072": "b10-r3s3",
    "L073": "b10-r3s4",
    "L074": "b10-r3s5",
    "L075": "b10-r3s5",
    "L076": "b10-r3s6",
    "L077": "b10-r3s7",
    "L078": "b10-r3s7",
    "L079": "b10-r3s8",
    "L080": "b10-r3s8",
    "L081": "b10-r3s9",
    "L082": "b10-r3s10",
    "L083": "b10-r3s11",
    "L084": "b27-r0",
    "L085": "b27-r1",
    "L086": "b27-r2",
    "L087": "b27-r3",
    "L088": "b27-r4",
    "L089": "b27-r5",
    "L090": "b30-r0",
    "L091": "b30-r1",
    "L092": "b30-r1",
    "L093": "b30-r2",
    "L094": "b30-r3",
    "L095": "b30-r4",
    "L096": "b30-r5",
    "L097": "b30-r6",
    "L098": "b30-r7",
    "L099": "b30-r7",
    "L100": "b34-r0",
    "L101": "b34-r1",
    "L102": "b34-r2",
    "L103": "b35-r0",
    "L104": "b35-r1",
    "L105": "b35-r1",
    "L106": "b35-r1",
    "L107": "b35-r2",
    "L108": "b35-r3",
    "L109": "b35-r4",
    "L110": "b35-r5",
    "L111": "b35-r6",
    "L112": "b35-r6",
    "L113": "b35-r7",
    "L114": "b35-r8",
    "L115": "b35-r9",
    "L116": "b35-r10",
    "L117": "b35-r11",
    "L118": "b35-r11",
    "L119": "b35-r12s0",
    "L120": "b35-r12s0",
    "L121": "b35-r12s1",
    "L122": "b35-r12s1",
    "L123": "b35-r13",
    "L124": "b35-r14",
    "L125": "b35-r15",
    "L126": "b35-r16",
    "L127": "b35-r17",
    "L128": "b35-r18s0",
    "L129": "b35-r18s1",
    "L130": "b35-r18s2",
    "L131": "b47-r0",
    "L132": "b47-r1",
    "L133": "b47-r2",
    "L134": "b47-r2",
    "L135": "b47-r3",
    "L136": "b47-r3",
    "L137": "b47-r4",
    "L138": "b47-r4",
    "L139": "b47-r5",
    "L140": "b47-r6",
    "L141": "b47-r7",
    "L142": "b48-r0",
    "L143": "b48-r0",
    "L144": "b48-r1",
    "L145": "b48-r2",
    "L146": "b48-r3",
    "L147": "b50-r0",
    "L148": "b50-r1",
    "L149": "b50-r2",
    "L150": "b50-r3",
    "L151": "b51-r0",
    "L152": "b51-r1",
    "L153": "b51-r2",
    "L154": "b51-r3",
    "L155": "b51-r4",
    "L156": "b51-r5",
    "L157": "b51-r6",
    "L158": "b51-r6",
    "L159": "b51-r7",
    "L160": "b51-r8",
    "L161": "b51-r8",
    "L162": "b51-r9",
    "L163": "b51-r10",
    "L164": "b51-r10",
    "L165": "b51-r11",
    "L166": "b51-r12",
    "L167": "b51-r13",
    "L168": "b51-r13",
    "L169": "b51-r13",
    "L170": "b51-r14",
    "L171": "b51-r15",
    "L172": "b51-r16",
    "L173": "b51-r17",
    "L174": "b51-r18",
    "L175": "b52-r0",
    "L176": "b52-r1",
    "L177": "b52-r2",
    "L178": "b52-r3",
    "L179": "b52-r4s0",
    "L180": "b52-r4s0",
    "L181": "b52-r4s1",
    "L182": "b52-r5s0",
    "L183": "b52-r5s0",
    "L184": "b52-r5s1",
    "L185": "b52-r6s0",
    "L186": "b52-r6s0",
    "L187": "b52-r6s1",
    "L188": "b52-r6s1",
    "L189": "b52-r7s0",
    "L190": "b52-r7s1",
    "L191": "b52-r8",
    "L192": "b52-r9s0",
    "L193": "b52-r9s1",
    "L194": "b52-r9s2",
    "L195": "b52-r9s2",
    "L196": "b52-r10s0",
    "L197": "b52-r10s1",
    "L198": "b52-r10s1",
    "L199": "b52-r10s2",
    "L200": "b52-r10s3",
    "L201": "b52-r11s0",
    "L202": "b52-r11s0",
    "L203": "b52-r11s1",
    "L204": "b52-r11s1",
    "L205": "b52-r12s0",
    "L206": "b52-r12s1",
    "L207": "b52-r13",
    "L208": "b52-r14",
    "L209": "b52-r15",
    "L210": "b52-r15",
    "L211": "b52-r16s0",
    "L212": "b52-r16s0",
    "L213": "b52-r16s1",
    "L214": "b52-r16s1",
    "L215": "b52-r16s2",
    "L216": "b52-r17s0",
    "L217": "b52-r17s1",
    "L218": "b52-r18s0",
    "L219": "b52-r18s1",
    "L220": "b52-r19",
    "L221": "b52-r19",
    "L222": "b52-r20",
    "L223": "b52-r21",
    "L224": "b52-r21",
    "L225": "b52-r22",
    "L226": "b52-r23",
    "L227": "b52-r24",
    "L228": "b52-r25",
    "L229": "b52-r26",
    "L230": "b52-r27",
    "L231": "b52-r28",
    "L232": "b52-r29",
    "L233": "b52-r29",
    "L234": "b59-r0",
    "L235": "b59-r1",
    "L236": "b59-r1",
    "L237": "b60-r0",
    "L238": "b60-r1",
    "L239": "b60-r2",
    "L240": "b60-r3",
    "L241": "b60-r4",
    "L242": "b60-r5s0",
    "L243": "b60-r5s1",
    "L244": "b60-r6s0",
    "L245": "b60-r6s0",
    "L246": "b60-r6s1",
    "L247": "b60-r7",
    "L248": "b60-r7",
    "L249": "b60-r8",
    "L250": "b62-r0",
    "L251": "b62-r1",
    "L252": "b62-r1",
    "L253": "b62-r2",
    "L254": "b62-r3",
    "L255": "b62-r4",
    "L256": "b62-r5",
    "L257": "b62-r6",
    "L258": "b62-r7",
    "L259": "b62-r7",
    "L260": "b62-r8",
    "L261": "b62-r9",
    "L262": "b62-r10",
    "L263": "b62-r11",
    "L264": "b62-r12",
    "L265": "b62-r12",
    "L266": "b62-r13",
    "L267": "b62-r13",
    "L268": "b62-r14s0",
    "L269": "b62-r14s0",
    "L270": "b62-r14s1",
    "L271": "b62-r15s0",
    "L272": "b62-r15s1",
    "L273": "b63-r0",
    "L274": "b63-r1",
    "L275": "b63-r2",
    "L276": "b63-r2",
    "L277": "b63-r3",
    "L278": "b63-r4",
    "L279": "b63-r5",
    "L280": "b63-r6s0",
    "L281": "b63-r6s1",
    "L282": "b63-r7",
    "L283": "b63-r8",
    "L284": "b63-r9",
    "L285": "b63-r10",
    "L286": "b63-r11",
    "L287": "b63-r12",
    "L288": "b63-r12",
    "L289": "b63-r13s0",
    "L290": "b63-r13s1",
    "L291": "b63-r14",
    "L292": "b63-r15s0",
    "L293": "b63-r15s1",
    "L294": "b63-r15s2",
    "L295": "b63-r15s3",
    "L296": "b63-r15s4",
    "L297": "b63-r15s5",
    "L298": "b63-r15s5",
    "L299": "b63-r15s6",
    "L300": "b63-r15s7",
    "L301": "b63-r15s7",
    "L302": "b63-r15s8",
    "L303": "b63-r15s8",
    "L304": "b63-r15s9",
    "L305": "b63-r15s10",
    "L306": "b63-r15s10",
    "L307": "b63-r15s11",
    "L308": "b63-r15s12",
    "L309": "b63-r16",
    "L310": "b63-r17",
    "L311": "b63-r18",
    "L312": "b63-r18",
    "L313": "b63-r19",
    "L314": "b63-r20",
    "L315": "b63-r21",
    "L316": "b63-r22",
    "L317": "b63-r22",
    "L318": "b63-r23",
    "L319": "b63-r24",
    "L320": "b63-r25",
    "L321": "b63-r26",
    "L322": "b63-r27",
    "L323": "b63-r28",
    "L324": "b63-r29",
    "L325": "b63-r29",
    "L326": "b63-r30",
    "L327": "b63-r31",
    "L328": "b63-r32",
    "L329": "b63-r33",
    "L330": "b63-r34s0",
    "L331": "b63-r34s1",
    "L332": "b64-r0",
    "L333": "b64-r1",
    "L334": "b64-r2",
    "L335": "b64-r3",
    "L336": "b64-r4",
    "L337": "b64-r5",
    "L338": "b64-r6",
    "L339": "b64-r7",
    "L340": "b64-r8",
    "L341": "b64-r9",
    "L342": "b64-r10",
    "L343": "b64-r11",
    "L344": "b64-r12",
    "L345": "b64-r13",
    "L346": "b64-r14",
    "L347": "b64-r15",
    "L348": "b64-r16",
    "L349": "b64-r17",
    "L350": "b64-r18",
    "L351": "b64-r19",
    "L352": "b64-r20",
    "L353": "b64-r21",
    "L354": "b64-r22",
    "L355": "b64-r23",
    "L356": "b64-r24",
    "L357": "b64-r25",
    "L358": "b64-r26",
    "L359": "b64-r27",
    "L360": "b64-r28",
    "L361": "b64-r29",
    "L362": "b64-r30",
    "L363": "b64-r31",
    "L364": "b64-r32",
    "L365": "b64-r33",
    "L366": "b64-r34",
    "L367": "b64-r35",
    "L368": "b64-r36",
    "L369": "b64-r37",
    "L370": "b64-r38",
    "L371": "b64-r39",
    "L372": "b64-r40",
    "L373": "b64-r41",
    "L374": "b64-r42",
    "L375": "b64-r43",
    "L376": "b64-r44",
    "L377": "b64-r45",
    "L378": "b64-r46",
    "L379": "b64-r47",
    "L380": "b64-r48",
    "L381": "b64-r49",
    "L382": "b64-r50",
    "L383": "b64-r51",
    "L384": "b64-r51",
    "L385": "b64-r52",
    "L386": "b64-r53",
    "L387": "b64-r54",
    "L388": "b64-r55",
    "L389": "b64-r56",
    "L390": "b64-r57",
    "L391": "b64-r58",
    "L392": "b64-r59",
    "L393": "b64-r60",
    "L394": "b64-r61",
    "L395": "b64-r61",
    "L396": "b64-r62",
    "L397": "b64-r63",
    "L398": "b64-r64",
    "L399": "b64-r64",
    "L400": "b64-r64",
    "L401": "b64-r64",
    "L402": "b64-r65s0",
    "L403": "b64-r65s0",
    "L404": "b64-r65s1",
    "L405": "b64-r65s1",
    "L406": "b64-r66",
    "L407": "b64-r66",
    "L408": "b64-r67",
    "L409": "b64-r68",
    "L410": "b64-r69",
    "L411": "b64-r70",
    "L412": "b64-r71",
    "L413": "b64-r72",
    "L414": "b64-r73",
    "L415": "b64-r74s0",
    "L416": "b64-r74s1",
    "L417": "b64-r75",
    "L418": "b64-r75",
    "L419": "b64-r76",
    "L420": "b64-r77",
    "L421": "b64-r78",
    "L422": "b64-r79s0",
    "L423": "b64-r79s0",
    "L424": "b64-r79s0",
    "L425": "b64-r79s1",
    "L426": "b64-r79s1",
    "L427": "b64-r79s1",
    "L428": "b64-r80",
    "L429": "b64-r80",
    "L430": "b64-r81",
    "L431": "b65-r0",
    "L432": "b65-r1",
    "L433": "b66-r0",
    "L434": "b66-r1",
    "L435": "b66-r1",
    "L436": "b66-r2",
    "L437": "b66-r2",
    "L438": "b66-r3",
    "L439": "b66-r4",
    "L440": "b66-r5",
    "L441": "b66-r6",
    "L442": "b66-r7",
    "L443": "b66-r8",
    "L444": "b66-r9s0",
    "L445": "b66-r9s1",
    "L446": "b66-r9s2",
    "L447": "b66-r9s3",
    "L448": "b66-r9s4",
    "L449": "b66-r9s4",
    "L450": "b66-r9s5",
    "L451": "b66-r9s6",
    "L452": "b66-r9s7",
    "L453": "b67-r0",
    "L454": "b67-r1",
    "L455": "b67-r2",
    "L456": "b67-r3",
    "L457": "b68-r0s0",
    "L458": "b68-r0s1",
    "L459": "b68-r0s2",
    "L460": "b69-r0",
    "L461": "b69-r1",
    "L462": "b70-r0",
    "L463": "b70-r0",
    "L464": "b70-r1",
    "L465": "b70-r2",
    "L466": "b70-r3",
    "L467": "b70-r4",
    "L468": "b70-r5",
    "L469": "b70-r5",
    "L470": "b71-r0",
    "L471": "b71-r1",
    "L472": "b71-r2",
    "L473": "b71-r3",
    "L474": "b71-r4",
    "L475": "b71-r5",
    "L476": "b71-r6",
    "L477": "b71-r7",
    "L478": "b71-r8",
    "L479": "b71-r9",
    "L480": "b71-r10",
    "L481": "b71-r11",
    "L482": "b71-r12",
    "L483": "b71-r13",
    "L484": "b71-r14",
    "L485": "b71-r15",
    "L486": "b71-r16",
    "L487": "b71-r16",
    "L488": "b71-r17",
    "L489": "b71-r18"
  }
}